google_takeout_viewer/__init__.py
google_takeout_viewer/cli.py
google_takeout_viewer/parsers.py
google_takeout_viewer/server.py
google_takeout_viewer/frontend_build/index.html
google_takeout_viewer/frontend_build/assets/index-DFXUNBbS.js
google_takeout_viewer/frontend_build/assets/index-DirdeFGx.css
google_takeout_viewer-0.1.3.dist-info/licenses/LICENSE
google_takeout_viewer-0.1.3.dist-info/METADATA
google_takeout_viewer-0.1.3.dist-info/WHEEL
google_takeout_viewer-0.1.3.dist-info/entry_points.txt
google_takeout_viewer-0.1.3.dist-info/top_level.txt
google_takeout_viewer-0.1.3.dist-info/RECORD
