Metadata-Version: 2.4
Name: google-takeout-viewer
Version: 0.1.3
Summary: A tool to visualize Google Takeout data
Author: Kiduzk
License-Expression: MIT
Project-URL: Repository, https://github.com/Kiduzk/google-takeout-viewer
Project-URL: Issues, https://github.com/Kiduzk/google-takeout-viewer/issues
Keywords: google,takeout,youtube,keep,parser,viewer,data-visualization
Classifier: Development Status :: 4 - Beta
Classifier: Environment :: Web Environment
Classifier: Intended Audience :: End Users/Desktop
Classifier: Natural Language :: English
Classifier: Operating System :: OS Independent
Classifier: Programming Language :: Python :: 3
Classifier: Programming Language :: Python :: 3.8
Classifier: Programming Language :: Python :: 3.9
Classifier: Programming Language :: Python :: 3.10
Classifier: Programming Language :: Python :: 3.11
Classifier: Programming Language :: Python :: 3.12
Classifier: Topic :: Internet
Classifier: Topic :: Utilities
Requires-Python: >=3.8
License-File: LICENSE
Requires-Dist: fastapi>=0.104.0
Requires-Dist: google-takeout-parser>=0.1.12
Requires-Dist: click>=8.1.0
Requires-Dist: peewee>=3.17.0
Requires-Dist: uvicorn[standard]>=0.24.0
Dynamic: license-file
